pyall/__init__.py
pyall/__main__.py
pyall/analyzer.py
pyall/color.py
pyall/config.py
pyall/constants.py
pyall/main.py
pyall/py.typed
pyall/refactor.py
pyall/relate.py
pyall/rule.py
pyall/session.py
pyall/typing.py
pyall/utils.py
pyall-0.3.5.dist-info/METADATA
pyall-0.3.5.dist-info/WHEEL
pyall-0.3.5.dist-info/entry_points.txt
pyall-0.3.5.dist-info/top_level.txt
pyall-0.3.5.dist-info/zip-safe
pyall-0.3.5.dist-info/RECORD
