Metadata-Version: 2.1
Name: pyall
Version: 0.3.5
Summary: attr: pyall.__description__
Home-page: https://pyall.hakancelik.dev/
Author: Hakan Celik
Author-email: hakancelikdev@gmail.com
License: GNU General Public License v3.0
Project-URL: Documentation, https://pyall.hakancelik.dev/
Project-URL: Issues, https://github.com/hakancelikdev/pyall/issues/
Project-URL: Changelog, https://pyall.hakancelik.dev/changelog
Keywords: all
Classifier: Development Status :: 1 - Planning
Classifier: License :: OSI Approved :: GNU General Public License v3 (GPLv3)
Classifier: Operating System :: OS Independent
Classifier: Programming Language :: Python
Classifier: Programming Language :: Python :: 3
Classifier: Programming Language :: Python :: 3 :: Only
Classifier: Programming Language :: Python :: 3.8
Classifier: Programming Language :: Python :: 3.9
Classifier: Programming Language :: Python :: 3.10
Classifier: Programming Language :: Python :: 3.11
Classifier: Programming Language :: Python :: Implementation :: CPython
Classifier: Environment :: Console
Classifier: Topic :: Software Development :: Libraries :: Python Modules
Requires-Python: >=3.8
Provides-Extra: docs
Requires-Dist: mkdocs (==1.3.0) ; extra == 'docs'
Requires-Dist: mkdocs-material (==8.3.6) ; extra == 'docs'
Requires-Dist: mkdocs-markdownextradata-plugin (==0.2.5) ; extra == 'docs'
Requires-Dist: mkdocs-minify-plugin (==0.5.0) ; extra == 'docs'
Requires-Dist: mkdocs-git-revision-date-localized-plugin (==1.0.1) ; extra == 'docs'
Provides-Extra: test
Requires-Dist: pytest (==6.2.4) ; extra == 'test'
Requires-Dist: pytest-cov (==2.12.1) ; extra == 'test'
